marlin/__init__.py
marlin/bookmark.py
marlin/manage.py
marlin/marlin_help.py
marlin/rmark.py
marlin/styles.py
marlin/__pycache__/__init__.cpython-38.pyc
marlin/__pycache__/bookmark.cpython-38.pyc
marlin/__pycache__/manage.cpython-38.pyc
marlin/__pycache__/marlin_help.cpython-38.pyc
marlin/__pycache__/styles.cpython-38.pyc
marlin/scripts/marlin.bat
marlin/scripts/marlin.sh
marlin_bookmark-0.1.6.data/scripts/marlin.bat
marlin_bookmark-0.1.6.dist-info/LICENSE
marlin_bookmark-0.1.6.dist-info/METADATA
marlin_bookmark-0.1.6.dist-info/WHEEL
marlin_bookmark-0.1.6.dist-info/entry_points.txt
marlin_bookmark-0.1.6.dist-info/top_level.txt
marlin_bookmark-0.1.6.dist-info/RECORD
