Metadata-Version: 2.1
Name: marlin-bookmark
Version: 0.1.6
Summary: Swim between bookmarks in the terminal
Home-page: https://github.com/wilfredinni/marlin
Author: Carlos Montecinos Geisse
Author-email: carlos.w.montecinos@gmail.com
License: MIT License
Platform: UNKNOWN
Classifier: Development Status :: 2 - Pre-Alpha
Classifier: Intended Audience :: Developers
Classifier: License :: OSI Approved :: MIT License
Classifier: Natural Language :: English
Classifier: Programming Language :: Python :: 3
Classifier: Programming Language :: Python :: 3.6
Classifier: Programming Language :: Python :: 3.7
Requires-Python: >=3
Requires-Dist: click
Requires-Dist: colorama
